README.md
setup.py
tests/__init__.py
tests/test_futures_public_api.py
tests/test_leverage_trade_api.py
tests/test_public_api.py
tests/test_trade_api.py
zaifapi/__init__.py
zaifapi/api_error.py
zaifapi/impl.py
zaifapi/oauth.py
zaifapi.egg-info/PKG-INFO
zaifapi.egg-info/SOURCES.txt
zaifapi.egg-info/dependency_links.txt
zaifapi.egg-info/requires.txt
zaifapi.egg-info/top_level.txt
zaifapi/api_common/__init__.py
zaifapi/api_common/response.py
zaifapi/api_common/url.py
zaifapi/api_common/validator.py
zaifapi/exchange_api/__init__.py
zaifapi/exchange_api/public.py
zaifapi/exchange_api/trade.py